x_scaffold/__init__.py
x_scaffold/__main__.py
x_scaffold/cli.py
x_scaffold/context.py
x_scaffold/engine.py
x_scaffold/git.py
x_scaffold/plugin.py
x_scaffold/plugins/__init__.py
x_scaffold/plugins/config.py
x_scaffold/plugins/core.py
x_scaffold/plugins/fetch.py
x_scaffold/plugins/github.py
x_scaffold/plugins/log.py
x_scaffold/plugins/scaffold.py
x_scaffold/plugins/shell.py
x_scaffold/rendering.py
x_scaffold/runtime.py
x_scaffold/steps.py
x_scaffold/utils.py
x_scaffold-2.0.12.dist-info/entry_points.txt
x_scaffold-2.0.12.dist-info/WHEEL
x_scaffold-2.0.12.dist-info/METADATA
x_scaffold-2.0.12.dist-info/RECORD
