Metadata-Version: 2.1
Name: x-scaffold
Version: 2.0.12
Summary: Used to scaffold directories or GitHub repositories.
Author: Dan Clayton
Author-email: dan@azwebmaster.com
Requires-Python: >=3.9,<4.0
Classifier: Programming Language :: Python :: 3
Classifier: Programming Language :: Python :: 3.10
Classifier: Programming Language :: Python :: 3.9
Requires-Dist: GitPython (>=3.1.24,<4.0.0)
Requires-Dist: Jinja2 (==3.0.3)
Requires-Dist: PyGithub (>=1.55,<2.0)
Requires-Dist: click (>=7.0.0,<8.0.0)
Requires-Dist: requests (>=2.27.1,<3.0.0)
Requires-Dist: ruamel.yaml (>=0.17.20,<0.18.0)
